senecalearning/__init__.py
senecalearning/seneca.py
senecalearning-1.0.20.dist-info/LICENSE
senecalearning-1.0.20.dist-info/METADATA
senecalearning-1.0.20.dist-info/WHEEL
senecalearning-1.0.20.dist-info/top_level.txt
senecalearning-1.0.20.dist-info/RECORD
