Metadata-Version: 2.1
Name: senecalearning
Version: 1.0.20
Summary: A small, unofficial python API for SenecaLearning
Home-page: https://github.com/wyatt/seneca
Author: Wyatt Sell
Author-email: wyatt@wyattsell.com
License: MIT License
Platform: UNKNOWN
Classifier: Development Status :: 4 - Beta
Classifier: License :: OSI Approved :: MIT License
Classifier: Programming Language :: Python :: 3 :: Only
Requires-Dist: requests
